{
    "command": "../workload_generation/generate_batsim_workload_from_oar_result.py -i4 -r ../replay_workload/results_2016-02-17--21-35-37/oar_gant_g5k_workload_delay2.json.details workloads/delay_seed2_size34.json",
    "date": "2016-04-10 15:36:42.069789",
    "description": "This workload has been generated from an OAR gantt output",
    "jobs": [
        {
            "id": 1008,
            "profile": "1008",
            "res": 4,
            "subtime": 3496.0,
            "walltime": 166.0
        },
        {
            "id": 1019,
            "profile": "1019",
            "res": 2,
            "subtime": 3711.0,
            "walltime": 264.0
        },
        {
            "id": 835,
            "profile": "835",
            "res": 1,
            "subtime": 117.0,
            "walltime": 92.0
        },
        {
            "id": 1012,
            "profile": "1012",
            "res": 2,
            "subtime": 3578.0,
            "walltime": 5935.0
        },
        {
            "id": 1045,
            "profile": "1045",
            "res": 2,
            "subtime": 4212.0,
            "walltime": 620.0
        },
        {
            "id": 1062,
            "profile": "1062",
            "res": 2,
            "subtime": 4539.0,
            "walltime": 620.0
        },
        {
            "id": 977,
            "profile": "977",
            "res": 4,
            "subtime": 2896.0,
            "walltime": 359.0
        },
        {
            "id": 891,
            "profile": "891",
            "res": 2,
            "subtime": 1210.0,
            "walltime": 264.0
        },
        {
            "id": 1024,
            "profile": "1024",
            "res": 4,
            "subtime": 3808.0,
            "walltime": 876.0
        },
        {
            "id": 961,
            "profile": "961",
            "res": 2,
            "subtime": 2585.0,
            "walltime": 264.0
        },
        {
            "id": 848,
            "profile": "848",
            "res": 1,
            "subtime": 374.0,
            "walltime": 885.0
        },
        {
            "id": 871,
            "profile": "871",
            "res": 2,
            "subtime": 821.0,
            "walltime": 5935.0
        },
        {
            "id": 1025,
            "profile": "1025",
            "res": 2,
            "subtime": 3822.0,
            "walltime": 2658.0
        },
        {
            "id": 1050,
            "profile": "1050",
            "res": 2,
            "subtime": 4304.0,
            "walltime": 264.0
        },
        {
            "id": 972,
            "profile": "972",
            "res": 8,
            "subtime": 2799.0,
            "walltime": 488.0
        },
        {
            "id": 1036,
            "profile": "1036",
            "res": 16,
            "subtime": 4034.0,
            "walltime": 60.0
        },
        {
            "id": 984,
            "profile": "984",
            "res": 2,
            "subtime": 3031.0,
            "walltime": 620.0
        },
        {
            "id": 950,
            "profile": "950",
            "res": 8,
            "subtime": 2364.0,
            "walltime": 60.0
        },
        {
            "id": 1009,
            "profile": "1009",
            "res": 4,
            "subtime": 3518.0,
            "walltime": 2905.0
        },
        {
            "id": 872,
            "profile": "872",
            "res": 2,
            "subtime": 841.0,
            "walltime": 5935.0
        },
        {
            "id": 876,
            "profile": "876",
            "res": 1,
            "subtime": 917.0,
            "walltime": 885.0
        },
        {
            "id": 877,
            "profile": "877",
            "res": 2,
            "subtime": 937.0,
            "walltime": 2658.0
        },
        {
            "id": 1042,
            "profile": "1042",
            "res": 1,
            "subtime": 4150.0,
            "walltime": 2799.0
        },
        {
            "id": 1071,
            "profile": "1071",
            "res": 2,
            "subtime": 4722.0,
            "walltime": 620.0
        },
        {
            "id": 1029,
            "profile": "1029",
            "res": 1,
            "subtime": 3901.0,
            "walltime": 3864.0
        },
        {
            "id": 1068,
            "profile": "1068",
            "res": 2,
            "subtime": 4660.0,
            "walltime": 1409.0
        },
        {
            "id": 974,
            "profile": "974",
            "res": 1,
            "subtime": 2839.0,
            "walltime": 11769.0
        },
        {
            "id": 903,
            "profile": "903",
            "res": 4,
            "subtime": 1445.0,
            "walltime": 2905.0
        },
        {
            "id": 886,
            "profile": "886",
            "res": 1,
            "subtime": 1115.0,
            "walltime": 11769.0
        },
        {
            "id": 870,
            "profile": "870",
            "res": 2,
            "subtime": 799.0,
            "walltime": 620.0
        },
        {
            "id": 1026,
            "profile": "1026",
            "res": 4,
            "subtime": 3841.0,
            "walltime": 2905.0
        },
        {
            "id": 853,
            "profile": "853",
            "res": 4,
            "subtime": 469.0,
            "walltime": 359.0
        },
        {
            "id": 917,
            "profile": "917",
            "res": 1,
            "subtime": 1721.0,
            "walltime": 92.0
        },
        {
            "id": 909,
            "profile": "909",
            "res": 4,
            "subtime": 1564.0,
            "walltime": 359.0
        },
        {
            "id": 959,
            "profile": "959",
            "res": 2,
            "subtime": 2545.0,
            "walltime": 2658.0
        },
        {
            "id": 906,
            "profile": "906",
            "res": 1,
            "subtime": 1504.0,
            "walltime": 92.0
        },
        {
            "id": 933,
            "profile": "933",
            "res": 1,
            "subtime": 2033.0,
            "walltime": 885.0
        },
        {
            "id": 1066,
            "profile": "1066",
            "res": 2,
            "subtime": 4619.0,
            "walltime": 1409.0
        },
        {
            "id": 854,
            "profile": "854",
            "res": 4,
            "subtime": 488.0,
            "walltime": 60.0
        },
        {
            "id": 924,
            "profile": "924",
            "res": 2,
            "subtime": 1860.0,
            "walltime": 2658.0
        },
        {
            "id": 1058,
            "profile": "1058",
            "res": 1,
            "subtime": 4461.0,
            "walltime": 885.0
        },
        {
            "id": 1053,
            "profile": "1053",
            "res": 1,
            "subtime": 4362.0,
            "walltime": 2799.0
        },
        {
            "id": 946,
            "profile": "946",
            "res": 2,
            "subtime": 2285.0,
            "walltime": 620.0
        },
        {
            "id": 862,
            "profile": "862",
            "res": 1,
            "subtime": 645.0,
            "walltime": 2799.0
        },
        {
            "id": 878,
            "profile": "878",
            "res": 1,
            "subtime": 957.0,
            "walltime": 2799.0
        },
        {
            "id": 832,
            "profile": "832",
            "res": 4,
            "subtime": 59.0,
            "walltime": 60.0
        },
        {
            "id": 1075,
            "profile": "1075",
            "res": 2,
            "subtime": 4798.0,
            "walltime": 66.0
        },
        {
            "id": 934,
            "profile": "934",
            "res": 2,
            "subtime": 2053.0,
            "walltime": 1409.0
        },
        {
            "id": 1077,
            "profile": "1077",
            "res": 8,
            "subtime": 4834.0,
            "walltime": 488.0
        },
        {
            "id": 890,
            "profile": "890",
            "res": 4,
            "subtime": 1190.0,
            "walltime": 876.0
        },
        {
            "id": 960,
            "profile": "960",
            "res": 1,
            "subtime": 2565.0,
            "walltime": 3864.0
        },
        {
            "id": 982,
            "profile": "982",
            "res": 2,
            "subtime": 2992.0,
            "walltime": 5935.0
        },
        {
            "id": 841,
            "profile": "841",
            "res": 4,
            "subtime": 233.0,
            "walltime": 2905.0
        },
        {
            "id": 1028,
            "profile": "1028",
            "res": 2,
            "subtime": 3882.0,
            "walltime": 264.0
        },
        {
            "id": 980,
            "profile": "980",
            "res": 2,
            "subtime": 2954.0,
            "walltime": 2658.0
        },
        {
            "id": 843,
            "profile": "843",
            "res": 8,
            "subtime": 275.0,
            "walltime": 1790.0
        },
        {
            "id": 981,
            "profile": "981",
            "res": 1,
            "subtime": 2974.0,
            "walltime": 885.0
        },
        {
            "id": 967,
            "profile": "967",
            "res": 2,
            "subtime": 2704.0,
            "walltime": 5935.0
        },
        {
            "id": 942,
            "profile": "942",
            "res": 2,
            "subtime": 2206.0,
            "walltime": 620.0
        },
        {
            "id": 916,
            "profile": "916",
            "res": 1,
            "subtime": 1702.0,
            "walltime": 2799.0
        },
        {
            "id": 912,
            "profile": "912",
            "res": 2,
            "subtime": 1622.0,
            "walltime": 620.0
        },
        {
            "id": 1015,
            "profile": "1015",
            "res": 2,
            "subtime": 3633.0,
            "walltime": 620.0
        },
        {
            "id": 1067,
            "profile": "1067",
            "res": 2,
            "subtime": 4640.0,
            "walltime": 66.0
        },
        {
            "id": 951,
            "profile": "951",
            "res": 4,
            "subtime": 2384.0,
            "walltime": 1519.0
        },
        {
            "id": 859,
            "profile": "859",
            "res": 2,
            "subtime": 588.0,
            "walltime": 264.0
        },
        {
            "id": 952,
            "profile": "952",
            "res": 1,
            "subtime": 2405.0,
            "walltime": 3864.0
        },
        {
            "id": 894,
            "profile": "894",
            "res": 1,
            "subtime": 1272.0,
            "walltime": 2799.0
        },
        {
            "id": 1003,
            "profile": "1003",
            "res": 2,
            "subtime": 3401.0,
            "walltime": 620.0
        },
        {
            "id": 874,
            "profile": "874",
            "res": 2,
            "subtime": 879.0,
            "walltime": 264.0
        },
        {
            "id": 932,
            "profile": "932",
            "res": 1,
            "subtime": 2014.0,
            "walltime": 11769.0
        },
        {
            "id": 883,
            "profile": "883",
            "res": 2,
            "subtime": 1055.0,
            "walltime": 1409.0
        },
        {
            "id": 988,
            "profile": "988",
            "res": 2,
            "subtime": 3105.0,
            "walltime": 264.0
        },
        {
            "id": 857,
            "profile": "857",
            "res": 2,
            "subtime": 549.0,
            "walltime": 5935.0
        },
        {
            "id": 994,
            "profile": "994",
            "res": 1,
            "subtime": 3221.0,
            "walltime": 2799.0
        },
        {
            "id": 1023,
            "profile": "1023",
            "res": 1,
            "subtime": 3788.0,
            "walltime": 92.0
        },
        {
            "id": 1030,
            "profile": "1030",
            "res": 2,
            "subtime": 3920.0,
            "walltime": 620.0
        },
        {
            "id": 863,
            "profile": "863",
            "res": 1,
            "subtime": 665.0,
            "walltime": 3864.0
        },
        {
            "id": 944,
            "profile": "944",
            "res": 2,
            "subtime": 2246.0,
            "walltime": 2658.0
        },
        {
            "id": 914,
            "profile": "914",
            "res": 1,
            "subtime": 1660.0,
            "walltime": 92.0
        },
        {
            "id": 837,
            "profile": "837",
            "res": 8,
            "subtime": 155.0,
            "walltime": 1790.0
        },
        {
            "id": 926,
            "profile": "926",
            "res": 2,
            "subtime": 1898.0,
            "walltime": 66.0
        },
        {
            "id": 861,
            "profile": "861",
            "res": 4,
            "subtime": 628.0,
            "walltime": 359.0
        },
        {
            "id": 882,
            "profile": "882",
            "res": 4,
            "subtime": 1036.0,
            "walltime": 359.0
        },
        {
            "id": 866,
            "profile": "866",
            "res": 2,
            "subtime": 722.0,
            "walltime": 2658.0
        },
        {
            "id": 953,
            "profile": "953",
            "res": 1,
            "subtime": 2426.0,
            "walltime": 11769.0
        },
        {
            "id": 910,
            "profile": "910",
            "res": 1,
            "subtime": 1584.0,
            "walltime": 11769.0
        },
        {
            "id": 1072,
            "profile": "1072",
            "res": 2,
            "subtime": 4742.0,
            "walltime": 264.0
        },
        {
            "id": 1049,
            "profile": "1049",
            "res": 2,
            "subtime": 4286.0,
            "walltime": 5935.0
        },
        {
            "id": 840,
            "profile": "840",
            "res": 2,
            "subtime": 212.0,
            "walltime": 66.0
        },
        {
            "id": 931,
            "profile": "931",
            "res": 1,
            "subtime": 1993.0,
            "walltime": 11769.0
        },
        {
            "id": 873,
            "profile": "873",
            "res": 2,
            "subtime": 859.0,
            "walltime": 1409.0
        },
        {
            "id": 1013,
            "profile": "1013",
            "res": 8,
            "subtime": 3597.0,
            "walltime": 60.0
        },
        {
            "id": 940,
            "profile": "940",
            "res": 2,
            "subtime": 2167.0,
            "walltime": 1409.0
        },
        {
            "id": 836,
            "profile": "836",
            "res": 2,
            "subtime": 136.0,
            "walltime": 1409.0
        },
        {
            "id": 1021,
            "profile": "1021",
            "res": 1,
            "subtime": 3752.0,
            "walltime": 92.0
        },
        {
            "id": 1035,
            "profile": "1035",
            "res": 1,
            "subtime": 4014.0,
            "walltime": 11769.0
        },
        {
            "id": 970,
            "profile": "970",
            "res": 4,
            "subtime": 2761.0,
            "walltime": 60.0
        },
        {
            "id": 923,
            "profile": "923",
            "res": 2,
            "subtime": 1841.0,
            "walltime": 620.0
        },
        {
            "id": 973,
            "profile": "973",
            "res": 4,
            "subtime": 2819.0,
            "walltime": 60.0
        },
        {
            "id": 1014,
            "profile": "1014",
            "res": 4,
            "subtime": 3618.0,
            "walltime": 60.0
        },
        {
            "id": 999,
            "profile": "999",
            "res": 2,
            "subtime": 3320.0,
            "walltime": 2658.0
        },
        {
            "id": 888,
            "profile": "888",
            "res": 4,
            "subtime": 1154.0,
            "walltime": 2905.0
        },
        {
            "id": 987,
            "profile": "987",
            "res": 2,
            "subtime": 3086.0,
            "walltime": 5935.0
        },
        {
            "id": 1020,
            "profile": "1020",
            "res": 4,
            "subtime": 3731.0,
            "walltime": 2905.0
        },
        {
            "id": 858,
            "profile": "858",
            "res": 8,
            "subtime": 568.0,
            "walltime": 1790.0
        },
        {
            "id": 851,
            "profile": "851",
            "res": 1,
            "subtime": 433.0,
            "walltime": 885.0
        },
        {
            "id": 928,
            "profile": "928",
            "res": 2,
            "subtime": 1934.0,
            "walltime": 1409.0
        },
        {
            "id": 1001,
            "profile": "1001",
            "res": 4,
            "subtime": 3362.0,
            "walltime": 60.0
        },
        {
            "id": 855,
            "profile": "855",
            "res": 1,
            "subtime": 508.0,
            "walltime": 2799.0
        },
        {
            "id": 927,
            "profile": "927",
            "res": 2,
            "subtime": 1917.0,
            "walltime": 66.0
        },
        {
            "id": 1039,
            "profile": "1039",
            "res": 1,
            "subtime": 4092.0,
            "walltime": 3864.0
        },
        {
            "id": 860,
            "profile": "860",
            "res": 2,
            "subtime": 606.0,
            "walltime": 2658.0
        },
        {
            "id": 842,
            "profile": "842",
            "res": 2,
            "subtime": 254.0,
            "walltime": 66.0
        },
        {
            "id": 969,
            "profile": "969",
            "res": 2,
            "subtime": 2741.0,
            "walltime": 1409.0
        },
        {
            "id": 1040,
            "profile": "1040",
            "res": 1,
            "subtime": 4112.0,
            "walltime": 885.0
        },
        {
            "id": 963,
            "profile": "963",
            "res": 2,
            "subtime": 2626.0,
            "walltime": 5935.0
        },
        {
            "id": 881,
            "profile": "881",
            "res": 2,
            "subtime": 1017.0,
            "walltime": 264.0
        },
        {
            "id": 1055,
            "profile": "1055",
            "res": 4,
            "subtime": 4403.0,
            "walltime": 2905.0
        },
        {
            "id": 1034,
            "profile": "1034",
            "res": 2,
            "subtime": 3995.0,
            "walltime": 620.0
        },
        {
            "id": 880,
            "profile": "880",
            "res": 2,
            "subtime": 997.0,
            "walltime": 5935.0
        },
        {
            "id": 901,
            "profile": "901",
            "res": 2,
            "subtime": 1407.0,
            "walltime": 264.0
        },
        {
            "id": 1011,
            "profile": "1011",
            "res": 2,
            "subtime": 3558.0,
            "walltime": 2658.0
        },
        {
            "id": 833,
            "profile": "833",
            "res": 2,
            "subtime": 80.0,
            "walltime": 66.0
        },
        {
            "id": 829,
            "profile": "829",
            "res": 4,
            "subtime": 0.0,
            "walltime": 60.0
        },
        {
            "id": 830,
            "profile": "830",
            "res": 1,
            "subtime": 20.0,
            "walltime": 885.0
        },
        {
            "id": 897,
            "profile": "897",
            "res": 8,
            "subtime": 1333.0,
            "walltime": 192.0
        },
        {
            "id": 991,
            "profile": "991",
            "res": 2,
            "subtime": 3165.0,
            "walltime": 620.0
        },
        {
            "id": 889,
            "profile": "889",
            "res": 2,
            "subtime": 1172.0,
            "walltime": 5935.0
        },
        {
            "id": 885,
            "profile": "885",
            "res": 4,
            "subtime": 1094.0,
            "walltime": 1519.0
        },
        {
            "id": 1032,
            "profile": "1032",
            "res": 4,
            "subtime": 3956.0,
            "walltime": 2905.0
        },
        {
            "id": 849,
            "profile": "849",
            "res": 2,
            "subtime": 393.0,
            "walltime": 2658.0
        },
        {
            "id": 918,
            "profile": "918",
            "res": 1,
            "subtime": 1740.0,
            "walltime": 3864.0
        },
        {
            "id": 1048,
            "profile": "1048",
            "res": 2,
            "subtime": 4267.0,
            "walltime": 1409.0
        },
        {
            "id": 939,
            "profile": "939",
            "res": 2,
            "subtime": 2146.0,
            "walltime": 1409.0
        },
        {
            "id": 902,
            "profile": "902",
            "res": 1,
            "subtime": 1425.0,
            "walltime": 92.0
        },
        {
            "id": 954,
            "profile": "954",
            "res": 8,
            "subtime": 2445.0,
            "walltime": 807.0
        },
        {
            "id": 1002,
            "profile": "1002",
            "res": 2,
            "subtime": 3381.0,
            "walltime": 2658.0
        },
        {
            "id": 930,
            "profile": "930",
            "res": 1,
            "subtime": 1973.0,
            "walltime": 2799.0
        },
        {
            "id": 838,
            "profile": "838",
            "res": 2,
            "subtime": 173.0,
            "walltime": 264.0
        },
        {
            "id": 869,
            "profile": "869",
            "res": 2,
            "subtime": 779.0,
            "walltime": 1409.0
        },
        {
            "id": 996,
            "profile": "996",
            "res": 2,
            "subtime": 3261.0,
            "walltime": 264.0
        },
        {
            "id": 900,
            "profile": "900",
            "res": 2,
            "subtime": 1390.0,
            "walltime": 5935.0
        },
        {
            "id": 993,
            "profile": "993",
            "res": 4,
            "subtime": 3203.0,
            "walltime": 876.0
        },
        {
            "id": 986,
            "profile": "986",
            "res": 4,
            "subtime": 3070.0,
            "walltime": 60.0
        },
        {
            "id": 856,
            "profile": "856",
            "res": 2,
            "subtime": 528.0,
            "walltime": 264.0
        },
        {
            "id": 965,
            "profile": "965",
            "res": 8,
            "subtime": 2665.0,
            "walltime": 1790.0
        },
        {
            "id": 936,
            "profile": "936",
            "res": 2,
            "subtime": 2094.0,
            "walltime": 620.0
        },
        {
            "id": 1007,
            "profile": "1007",
            "res": 4,
            "subtime": 3478.0,
            "walltime": 359.0
        },
        {
            "id": 947,
            "profile": "947",
            "res": 2,
            "subtime": 2304.0,
            "walltime": 66.0
        },
        {
            "id": 898,
            "profile": "898",
            "res": 4,
            "subtime": 1353.0,
            "walltime": 876.0
        },
        {
            "id": 989,
            "profile": "989",
            "res": 1,
            "subtime": 3124.0,
            "walltime": 3864.0
        },
        {
            "id": 867,
            "profile": "867",
            "res": 1,
            "subtime": 742.0,
            "walltime": 885.0
        },
        {
            "id": 925,
            "profile": "925",
            "res": 2,
            "subtime": 1879.0,
            "walltime": 1409.0
        },
        {
            "id": 844,
            "profile": "844",
            "res": 2,
            "subtime": 295.0,
            "walltime": 5935.0
        },
        {
            "id": 904,
            "profile": "904",
            "res": 4,
            "subtime": 1465.0,
            "walltime": 166.0
        },
        {
            "id": 908,
            "profile": "908",
            "res": 2,
            "subtime": 1544.0,
            "walltime": 66.0
        },
        {
            "id": 1046,
            "profile": "1046",
            "res": 1,
            "subtime": 4228.0,
            "walltime": 885.0
        },
        {
            "id": 846,
            "profile": "846",
            "res": 2,
            "subtime": 336.0,
            "walltime": 620.0
        },
        {
            "id": 847,
            "profile": "847",
            "res": 1,
            "subtime": 355.0,
            "walltime": 92.0
        },
        {
            "id": 850,
            "profile": "850",
            "res": 1,
            "subtime": 414.0,
            "walltime": 885.0
        },
        {
            "id": 1041,
            "profile": "1041",
            "res": 1,
            "subtime": 4130.0,
            "walltime": 11769.0
        },
        {
            "id": 1059,
            "profile": "1059",
            "res": 2,
            "subtime": 4478.0,
            "walltime": 2658.0
        },
        {
            "id": 919,
            "profile": "919",
            "res": 4,
            "subtime": 1761.0,
            "walltime": 1519.0
        },
        {
            "id": 852,
            "profile": "852",
            "res": 1,
            "subtime": 454.0,
            "walltime": 3864.0
        },
        {
            "id": 1006,
            "profile": "1006",
            "res": 1,
            "subtime": 3459.0,
            "walltime": 11769.0
        },
        {
            "id": 1078,
            "profile": "1078",
            "res": 4,
            "subtime": 4855.0,
            "walltime": 2905.0
        },
        {
            "id": 1005,
            "profile": "1005",
            "res": 2,
            "subtime": 3440.0,
            "walltime": 264.0
        },
        {
            "id": 1051,
            "profile": "1051",
            "res": 2,
            "subtime": 4323.0,
            "walltime": 1409.0
        },
        {
            "id": 1000,
            "profile": "1000",
            "res": 1,
            "subtime": 3341.0,
            "walltime": 92.0
        },
        {
            "id": 1054,
            "profile": "1054",
            "res": 4,
            "subtime": 4381.0,
            "walltime": 876.0
        },
        {
            "id": 937,
            "profile": "937",
            "res": 2,
            "subtime": 2112.0,
            "walltime": 620.0
        },
        {
            "id": 975,
            "profile": "975",
            "res": 2,
            "subtime": 2859.0,
            "walltime": 264.0
        },
        {
            "id": 943,
            "profile": "943",
            "res": 2,
            "subtime": 2226.0,
            "walltime": 264.0
        },
        {
            "id": 922,
            "profile": "922",
            "res": 8,
            "subtime": 1822.0,
            "walltime": 1790.0
        },
        {
            "id": 1063,
            "profile": "1063",
            "res": 4,
            "subtime": 4559.0,
            "walltime": 60.0
        },
        {
            "id": 956,
            "profile": "956",
            "res": 1,
            "subtime": 2485.0,
            "walltime": 92.0
        },
        {
            "id": 1038,
            "profile": "1038",
            "res": 2,
            "subtime": 4076.0,
            "walltime": 620.0
        },
        {
            "id": 875,
            "profile": "875",
            "res": 1,
            "subtime": 899.0,
            "walltime": 92.0
        },
        {
            "id": 1076,
            "profile": "1076",
            "res": 2,
            "subtime": 4815.0,
            "walltime": 264.0
        },
        {
            "id": 997,
            "profile": "997",
            "res": 1,
            "subtime": 3279.0,
            "walltime": 11769.0
        },
        {
            "id": 1056,
            "profile": "1056",
            "res": 2,
            "subtime": 4422.0,
            "walltime": 5935.0
        },
        {
            "id": 949,
            "profile": "949",
            "res": 2,
            "subtime": 2344.0,
            "walltime": 620.0
        },
        {
            "id": 1061,
            "profile": "1061",
            "res": 2,
            "subtime": 4519.0,
            "walltime": 620.0
        },
        {
            "id": 1073,
            "profile": "1073",
            "res": 8,
            "subtime": 4761.0,
            "walltime": 1790.0
        },
        {
            "id": 983,
            "profile": "983",
            "res": 2,
            "subtime": 3011.0,
            "walltime": 66.0
        },
        {
            "id": 884,
            "profile": "884",
            "res": 2,
            "subtime": 1074.0,
            "walltime": 66.0
        },
        {
            "id": 945,
            "profile": "945",
            "res": 2,
            "subtime": 2265.0,
            "walltime": 66.0
        },
        {
            "id": 962,
            "profile": "962",
            "res": 2,
            "subtime": 2606.0,
            "walltime": 264.0
        },
        {
            "id": 911,
            "profile": "911",
            "res": 8,
            "subtime": 1601.0,
            "walltime": 21908.0
        },
        {
            "id": 1037,
            "profile": "1037",
            "res": 1,
            "subtime": 4055.0,
            "walltime": 3864.0
        },
        {
            "id": 895,
            "profile": "895",
            "res": 2,
            "subtime": 1293.0,
            "walltime": 5935.0
        },
        {
            "id": 971,
            "profile": "971",
            "res": 2,
            "subtime": 2779.0,
            "walltime": 2658.0
        },
        {
            "id": 1057,
            "profile": "1057",
            "res": 2,
            "subtime": 4440.0,
            "walltime": 66.0
        },
        {
            "id": 864,
            "profile": "864",
            "res": 4,
            "subtime": 684.0,
            "walltime": 166.0
        },
        {
            "id": 1070,
            "profile": "1070",
            "res": 2,
            "subtime": 4702.0,
            "walltime": 2658.0
        },
        {
            "id": 966,
            "profile": "966",
            "res": 1,
            "subtime": 2684.0,
            "walltime": 885.0
        },
        {
            "id": 941,
            "profile": "941",
            "res": 2,
            "subtime": 2186.0,
            "walltime": 2658.0
        },
        {
            "id": 920,
            "profile": "920",
            "res": 1,
            "subtime": 1781.0,
            "walltime": 11769.0
        },
        {
            "id": 1047,
            "profile": "1047",
            "res": 1,
            "subtime": 4247.0,
            "walltime": 3864.0
        },
        {
            "id": 896,
            "profile": "896",
            "res": 2,
            "subtime": 1314.0,
            "walltime": 264.0
        },
        {
            "id": 1052,
            "profile": "1052",
            "res": 1,
            "subtime": 4343.0,
            "walltime": 885.0
        },
        {
            "id": 976,
            "profile": "976",
            "res": 2,
            "subtime": 2878.0,
            "walltime": 1409.0
        },
        {
            "id": 958,
            "profile": "958",
            "res": 1,
            "subtime": 2525.0,
            "walltime": 2799.0
        },
        {
            "id": 893,
            "profile": "893",
            "res": 1,
            "subtime": 1251.0,
            "walltime": 3864.0
        },
        {
            "id": 845,
            "profile": "845",
            "res": 4,
            "subtime": 316.0,
            "walltime": 60.0
        },
        {
            "id": 935,
            "profile": "935",
            "res": 2,
            "subtime": 2073.0,
            "walltime": 1409.0
        },
        {
            "id": 1074,
            "profile": "1074",
            "res": 2,
            "subtime": 4777.0,
            "walltime": 2658.0
        },
        {
            "id": 1004,
            "profile": "1004",
            "res": 2,
            "subtime": 3419.0,
            "walltime": 66.0
        },
        {
            "id": 992,
            "profile": "992",
            "res": 1,
            "subtime": 3185.0,
            "walltime": 3864.0
        },
        {
            "id": 1022,
            "profile": "1022",
            "res": 4,
            "subtime": 3769.0,
            "walltime": 60.0
        },
        {
            "id": 1060,
            "profile": "1060",
            "res": 1,
            "subtime": 4499.0,
            "walltime": 3864.0
        },
        {
            "id": 892,
            "profile": "892",
            "res": 4,
            "subtime": 1231.0,
            "walltime": 2905.0
        },
        {
            "id": 957,
            "profile": "957",
            "res": 1,
            "subtime": 2506.0,
            "walltime": 92.0
        },
        {
            "id": 865,
            "profile": "865",
            "res": 2,
            "subtime": 702.0,
            "walltime": 2658.0
        },
        {
            "id": 929,
            "profile": "929",
            "res": 4,
            "subtime": 1952.0,
            "walltime": 1519.0
        },
        {
            "id": 921,
            "profile": "921",
            "res": 4,
            "subtime": 1802.0,
            "walltime": 2905.0
        },
        {
            "id": 1069,
            "profile": "1069",
            "res": 2,
            "subtime": 4681.0,
            "walltime": 2658.0
        },
        {
            "id": 831,
            "profile": "831",
            "res": 1,
            "subtime": 40.0,
            "walltime": 2799.0
        },
        {
            "id": 899,
            "profile": "899",
            "res": 4,
            "subtime": 1373.0,
            "walltime": 876.0
        },
        {
            "id": 964,
            "profile": "964",
            "res": 1,
            "subtime": 2646.0,
            "walltime": 11769.0
        },
        {
            "id": 978,
            "profile": "978",
            "res": 2,
            "subtime": 2915.0,
            "walltime": 620.0
        },
        {
            "id": 979,
            "profile": "979",
            "res": 8,
            "subtime": 2935.0,
            "walltime": 192.0
        },
        {
            "id": 868,
            "profile": "868",
            "res": 2,
            "subtime": 762.0,
            "walltime": 2658.0
        },
        {
            "id": 887,
            "profile": "887",
            "res": 2,
            "subtime": 1135.0,
            "walltime": 2658.0
        },
        {
            "id": 913,
            "profile": "913",
            "res": 1,
            "subtime": 1643.0,
            "walltime": 2799.0
        },
        {
            "id": 907,
            "profile": "907",
            "res": 1,
            "subtime": 1524.0,
            "walltime": 11769.0
        },
        {
            "id": 985,
            "profile": "985",
            "res": 1,
            "subtime": 3050.0,
            "walltime": 92.0
        },
        {
            "id": 879,
            "profile": "879",
            "res": 2,
            "subtime": 975.0,
            "walltime": 264.0
        },
        {
            "id": 1064,
            "profile": "1064",
            "res": 1,
            "subtime": 4580.0,
            "walltime": 92.0
        },
        {
            "id": 968,
            "profile": "968",
            "res": 2,
            "subtime": 2720.0,
            "walltime": 5935.0
        },
        {
            "id": 995,
            "profile": "995",
            "res": 2,
            "subtime": 3240.0,
            "walltime": 1409.0
        },
        {
            "id": 948,
            "profile": "948",
            "res": 4,
            "subtime": 2324.0,
            "walltime": 359.0
        },
        {
            "id": 915,
            "profile": "915",
            "res": 2,
            "subtime": 1680.0,
            "walltime": 66.0
        },
        {
            "id": 1010,
            "profile": "1010",
            "res": 4,
            "subtime": 3538.0,
            "walltime": 2905.0
        },
        {
            "id": 1027,
            "profile": "1027",
            "res": 4,
            "subtime": 3861.0,
            "walltime": 1519.0
        },
        {
            "id": 1065,
            "profile": "1065",
            "res": 2,
            "subtime": 4600.0,
            "walltime": 264.0
        },
        {
            "id": 834,
            "profile": "834",
            "res": 4,
            "subtime": 99.0,
            "walltime": 1519.0
        },
        {
            "id": 955,
            "profile": "955",
            "res": 2,
            "subtime": 2465.0,
            "walltime": 264.0
        },
        {
            "id": 839,
            "profile": "839",
            "res": 4,
            "subtime": 192.0,
            "walltime": 876.0
        },
        {
            "id": 1017,
            "profile": "1017",
            "res": 2,
            "subtime": 3671.0,
            "walltime": 1409.0
        },
        {
            "id": 1031,
            "profile": "1031",
            "res": 2,
            "subtime": 3938.0,
            "walltime": 264.0
        },
        {
            "id": 1044,
            "profile": "1044",
            "res": 2,
            "subtime": 4191.0,
            "walltime": 620.0
        },
        {
            "id": 1043,
            "profile": "1043",
            "res": 1,
            "subtime": 4170.0,
            "walltime": 11769.0
        },
        {
            "id": 990,
            "profile": "990",
            "res": 1,
            "subtime": 3144.0,
            "walltime": 11769.0
        },
        {
            "id": 938,
            "profile": "938",
            "res": 2,
            "subtime": 2130.0,
            "walltime": 264.0
        },
        {
            "id": 1016,
            "profile": "1016",
            "res": 2,
            "subtime": 3652.0,
            "walltime": 264.0
        },
        {
            "id": 1033,
            "profile": "1033",
            "res": 1,
            "subtime": 3975.0,
            "walltime": 2799.0
        },
        {
            "id": 1018,
            "profile": "1018",
            "res": 2,
            "subtime": 3691.0,
            "walltime": 66.0
        },
        {
            "id": 905,
            "profile": "905",
            "res": 2,
            "subtime": 1485.0,
            "walltime": 264.0
        },
        {
            "id": 998,
            "profile": "998",
            "res": 8,
            "subtime": 3300.0,
            "walltime": 1790.0
        }
    ],
    "nb_res": 34,
    "profiles": {
        "1000": {
            "delay": 10.0,
            "type": "delay"
        },
        "1001": {
            "delay": 5.0,
            "type": "delay"
        },
        "1002": {
            "delay": 266.0,
            "type": "delay"
        },
        "1003": {
            "delay": 62.0,
            "type": "delay"
        },
        "1004": {
            "delay": 7.0,
            "type": "delay"
        },
        "1005": {
            "delay": 26.0,
            "type": "delay"
        },
        "1006": {
            "delay": 1189.0,
            "type": "delay"
        },
        "1007": {
            "delay": 36.0,
            "type": "delay"
        },
        "1008": {
            "delay": 17.0,
            "type": "delay"
        },
        "1009": {
            "delay": 291.0,
            "type": "delay"
        },
        "1010": {
            "delay": 291.0,
            "type": "delay"
        },
        "1011": {
            "delay": 266.0,
            "type": "delay"
        },
        "1012": {
            "delay": 592.0,
            "type": "delay"
        },
        "1013": {
            "delay": 3.0,
            "type": "delay"
        },
        "1014": {
            "delay": 4.0,
            "type": "delay"
        },
        "1015": {
            "delay": 62.0,
            "type": "delay"
        },
        "1016": {
            "delay": 27.0,
            "type": "delay"
        },
        "1017": {
            "delay": 142.0,
            "type": "delay"
        },
        "1018": {
            "delay": 7.0,
            "type": "delay"
        },
        "1019": {
            "delay": 26.0,
            "type": "delay"
        },
        "1020": {
            "delay": 291.0,
            "type": "delay"
        },
        "1021": {
            "delay": 10.0,
            "type": "delay"
        },
        "1022": {
            "delay": 4.0,
            "type": "delay"
        },
        "1023": {
            "delay": 10.0,
            "type": "delay"
        },
        "1024": {
            "delay": 89.0,
            "type": "delay"
        },
        "1025": {
            "delay": 266.0,
            "type": "delay"
        },
        "1026": {
            "delay": 291.0,
            "type": "delay"
        },
        "1027": {
            "delay": 152.0,
            "type": "delay"
        },
        "1028": {
            "delay": 29.0,
            "type": "delay"
        },
        "1029": {
            "delay": 388.0,
            "type": "delay"
        },
        "1030": {
            "delay": 63.0,
            "type": "delay"
        },
        "1031": {
            "delay": 27.0,
            "type": "delay"
        },
        "1032": {
            "delay": 304.0,
            "type": "delay"
        },
        "1033": {
            "delay": 281.0,
            "type": "delay"
        },
        "1034": {
            "delay": 63.0,
            "type": "delay"
        },
        "1035": {
            "delay": 1177.0,
            "type": "delay"
        },
        "1036": {
            "delay": 2.0,
            "type": "delay"
        },
        "1037": {
            "delay": 388.0,
            "type": "delay"
        },
        "1038": {
            "delay": 63.0,
            "type": "delay"
        },
        "1039": {
            "delay": 387.0,
            "type": "delay"
        },
        "1040": {
            "delay": 89.0,
            "type": "delay"
        },
        "1041": {
            "delay": 1179.0,
            "type": "delay"
        },
        "1042": {
            "delay": 281.0,
            "type": "delay"
        },
        "1043": {
            "delay": 1181.0,
            "type": "delay"
        },
        "1044": {
            "delay": 63.0,
            "type": "delay"
        },
        "1045": {
            "delay": 63.0,
            "type": "delay"
        },
        "1046": {
            "delay": 89.0,
            "type": "delay"
        },
        "1047": {
            "delay": 388.0,
            "type": "delay"
        },
        "1048": {
            "delay": 142.0,
            "type": "delay"
        },
        "1049": {
            "delay": 593.0,
            "type": "delay"
        },
        "1050": {
            "delay": 27.0,
            "type": "delay"
        },
        "1051": {
            "delay": 142.0,
            "type": "delay"
        },
        "1052": {
            "delay": 89.0,
            "type": "delay"
        },
        "1053": {
            "delay": 280.0,
            "type": "delay"
        },
        "1054": {
            "delay": 88.0,
            "type": "delay"
        },
        "1055": {
            "delay": 304.0,
            "type": "delay"
        },
        "1056": {
            "delay": 590.0,
            "type": "delay"
        },
        "1057": {
            "delay": 7.0,
            "type": "delay"
        },
        "1058": {
            "delay": 89.0,
            "type": "delay"
        },
        "1059": {
            "delay": 266.0,
            "type": "delay"
        },
        "1060": {
            "delay": 387.0,
            "type": "delay"
        },
        "1061": {
            "delay": 63.0,
            "type": "delay"
        },
        "1062": {
            "delay": 63.0,
            "type": "delay"
        },
        "1063": {
            "delay": 4.0,
            "type": "delay"
        },
        "1064": {
            "delay": 10.0,
            "type": "delay"
        },
        "1065": {
            "delay": 27.0,
            "type": "delay"
        },
        "1066": {
            "delay": 142.0,
            "type": "delay"
        },
        "1067": {
            "delay": 7.0,
            "type": "delay"
        },
        "1068": {
            "delay": 142.0,
            "type": "delay"
        },
        "1069": {
            "delay": 265.0,
            "type": "delay"
        },
        "1070": {
            "delay": 266.0,
            "type": "delay"
        },
        "1071": {
            "delay": 64.0,
            "type": "delay"
        },
        "1072": {
            "delay": 27.0,
            "type": "delay"
        },
        "1073": {
            "delay": 183.0,
            "type": "delay"
        },
        "1074": {
            "delay": 266.0,
            "type": "delay"
        },
        "1075": {
            "delay": 7.0,
            "type": "delay"
        },
        "1076": {
            "delay": 27.0,
            "type": "delay"
        },
        "1077": {
            "delay": 50.0,
            "type": "delay"
        },
        "1078": {
            "delay": 291.0,
            "type": "delay"
        },
        "829": {
            "delay": 4.0,
            "type": "delay"
        },
        "830": {
            "delay": 89.0,
            "type": "delay"
        },
        "831": {
            "delay": 281.0,
            "type": "delay"
        },
        "832": {
            "delay": 4.0,
            "type": "delay"
        },
        "833": {
            "delay": 7.0,
            "type": "delay"
        },
        "834": {
            "delay": 151.0,
            "type": "delay"
        },
        "835": {
            "delay": 9.0,
            "type": "delay"
        },
        "836": {
            "delay": 142.0,
            "type": "delay"
        },
        "837": {
            "delay": 179.0,
            "type": "delay"
        },
        "838": {
            "delay": 27.0,
            "type": "delay"
        },
        "839": {
            "delay": 92.0,
            "type": "delay"
        },
        "840": {
            "delay": 7.0,
            "type": "delay"
        },
        "841": {
            "delay": 291.0,
            "type": "delay"
        },
        "842": {
            "delay": 7.0,
            "type": "delay"
        },
        "843": {
            "delay": 182.0,
            "type": "delay"
        },
        "844": {
            "delay": 595.0,
            "type": "delay"
        },
        "845": {
            "delay": 4.0,
            "type": "delay"
        },
        "846": {
            "delay": 62.0,
            "type": "delay"
        },
        "847": {
            "delay": 10.0,
            "type": "delay"
        },
        "848": {
            "delay": 89.0,
            "type": "delay"
        },
        "849": {
            "delay": 266.0,
            "type": "delay"
        },
        "850": {
            "delay": 89.0,
            "type": "delay"
        },
        "851": {
            "delay": 89.0,
            "type": "delay"
        },
        "852": {
            "delay": 387.0,
            "type": "delay"
        },
        "853": {
            "delay": 37.0,
            "type": "delay"
        },
        "854": {
            "delay": 5.0,
            "type": "delay"
        },
        "855": {
            "delay": 278.0,
            "type": "delay"
        },
        "856": {
            "delay": 27.0,
            "type": "delay"
        },
        "857": {
            "delay": 597.0,
            "type": "delay"
        },
        "858": {
            "delay": 179.0,
            "type": "delay"
        },
        "859": {
            "delay": 29.0,
            "type": "delay"
        },
        "860": {
            "delay": 266.0,
            "type": "delay"
        },
        "861": {
            "delay": 37.0,
            "type": "delay"
        },
        "862": {
            "delay": 279.0,
            "type": "delay"
        },
        "863": {
            "delay": 388.0,
            "type": "delay"
        },
        "864": {
            "delay": 17.0,
            "type": "delay"
        },
        "865": {
            "delay": 266.0,
            "type": "delay"
        },
        "866": {
            "delay": 266.0,
            "type": "delay"
        },
        "867": {
            "delay": 93.0,
            "type": "delay"
        },
        "868": {
            "delay": 266.0,
            "type": "delay"
        },
        "869": {
            "delay": 141.0,
            "type": "delay"
        },
        "870": {
            "delay": 62.0,
            "type": "delay"
        },
        "871": {
            "delay": 593.0,
            "type": "delay"
        },
        "872": {
            "delay": 623.0,
            "type": "delay"
        },
        "873": {
            "delay": 142.0,
            "type": "delay"
        },
        "874": {
            "delay": 27.0,
            "type": "delay"
        },
        "875": {
            "delay": 10.0,
            "type": "delay"
        },
        "876": {
            "delay": 89.0,
            "type": "delay"
        },
        "877": {
            "delay": 266.0,
            "type": "delay"
        },
        "878": {
            "delay": 280.0,
            "type": "delay"
        },
        "879": {
            "delay": 27.0,
            "type": "delay"
        },
        "880": {
            "delay": 594.0,
            "type": "delay"
        },
        "881": {
            "delay": 27.0,
            "type": "delay"
        },
        "882": {
            "delay": 36.0,
            "type": "delay"
        },
        "883": {
            "delay": 141.0,
            "type": "delay"
        },
        "884": {
            "delay": 7.0,
            "type": "delay"
        },
        "885": {
            "delay": 153.0,
            "type": "delay"
        },
        "886": {
            "delay": 1176.0,
            "type": "delay"
        },
        "887": {
            "delay": 266.0,
            "type": "delay"
        },
        "888": {
            "delay": 290.0,
            "type": "delay"
        },
        "889": {
            "delay": 592.0,
            "type": "delay"
        },
        "890": {
            "delay": 89.0,
            "type": "delay"
        },
        "891": {
            "delay": 27.0,
            "type": "delay"
        },
        "892": {
            "delay": 291.0,
            "type": "delay"
        },
        "893": {
            "delay": 388.0,
            "type": "delay"
        },
        "894": {
            "delay": 281.0,
            "type": "delay"
        },
        "895": {
            "delay": 596.0,
            "type": "delay"
        },
        "896": {
            "delay": 27.0,
            "type": "delay"
        },
        "897": {
            "delay": 20.0,
            "type": "delay"
        },
        "898": {
            "delay": 90.0,
            "type": "delay"
        },
        "899": {
            "delay": 91.0,
            "type": "delay"
        },
        "900": {
            "delay": 592.0,
            "type": "delay"
        },
        "901": {
            "delay": 27.0,
            "type": "delay"
        },
        "902": {
            "delay": 10.0,
            "type": "delay"
        },
        "903": {
            "delay": 291.0,
            "type": "delay"
        },
        "904": {
            "delay": 17.0,
            "type": "delay"
        },
        "905": {
            "delay": 26.0,
            "type": "delay"
        },
        "906": {
            "delay": 9.0,
            "type": "delay"
        },
        "907": {
            "delay": 1180.0,
            "type": "delay"
        },
        "908": {
            "delay": 7.0,
            "type": "delay"
        },
        "909": {
            "delay": 37.0,
            "type": "delay"
        },
        "910": {
            "delay": 1177.0,
            "type": "delay"
        },
        "911": {
            "delay": 2244.0,
            "type": "delay"
        },
        "912": {
            "delay": 63.0,
            "type": "delay"
        },
        "913": {
            "delay": 280.0,
            "type": "delay"
        },
        "914": {
            "delay": 9.0,
            "type": "delay"
        },
        "915": {
            "delay": 7.0,
            "type": "delay"
        },
        "916": {
            "delay": 279.0,
            "type": "delay"
        },
        "917": {
            "delay": 10.0,
            "type": "delay"
        },
        "918": {
            "delay": 387.0,
            "type": "delay"
        },
        "919": {
            "delay": 153.0,
            "type": "delay"
        },
        "920": {
            "delay": 1180.0,
            "type": "delay"
        },
        "921": {
            "delay": 291.0,
            "type": "delay"
        },
        "922": {
            "delay": 183.0,
            "type": "delay"
        },
        "923": {
            "delay": 65.0,
            "type": "delay"
        },
        "924": {
            "delay": 267.0,
            "type": "delay"
        },
        "925": {
            "delay": 141.0,
            "type": "delay"
        },
        "926": {
            "delay": 7.0,
            "type": "delay"
        },
        "927": {
            "delay": 8.0,
            "type": "delay"
        },
        "928": {
            "delay": 141.0,
            "type": "delay"
        },
        "929": {
            "delay": 152.0,
            "type": "delay"
        },
        "930": {
            "delay": 279.0,
            "type": "delay"
        },
        "931": {
            "delay": 1176.0,
            "type": "delay"
        },
        "932": {
            "delay": 1177.0,
            "type": "delay"
        },
        "933": {
            "delay": 90.0,
            "type": "delay"
        },
        "934": {
            "delay": 142.0,
            "type": "delay"
        },
        "935": {
            "delay": 142.0,
            "type": "delay"
        },
        "936": {
            "delay": 63.0,
            "type": "delay"
        },
        "937": {
            "delay": 62.0,
            "type": "delay"
        },
        "938": {
            "delay": 27.0,
            "type": "delay"
        },
        "939": {
            "delay": 144.0,
            "type": "delay"
        },
        "940": {
            "delay": 141.0,
            "type": "delay"
        },
        "941": {
            "delay": 266.0,
            "type": "delay"
        },
        "942": {
            "delay": 62.0,
            "type": "delay"
        },
        "943": {
            "delay": 27.0,
            "type": "delay"
        },
        "944": {
            "delay": 266.0,
            "type": "delay"
        },
        "945": {
            "delay": 7.0,
            "type": "delay"
        },
        "946": {
            "delay": 62.0,
            "type": "delay"
        },
        "947": {
            "delay": 7.0,
            "type": "delay"
        },
        "948": {
            "delay": 37.0,
            "type": "delay"
        },
        "949": {
            "delay": 63.0,
            "type": "delay"
        },
        "950": {
            "delay": 3.0,
            "type": "delay"
        },
        "951": {
            "delay": 152.0,
            "type": "delay"
        },
        "952": {
            "delay": 387.0,
            "type": "delay"
        },
        "953": {
            "delay": 1178.0,
            "type": "delay"
        },
        "954": {
            "delay": 83.0,
            "type": "delay"
        },
        "955": {
            "delay": 27.0,
            "type": "delay"
        },
        "956": {
            "delay": 10.0,
            "type": "delay"
        },
        "957": {
            "delay": 10.0,
            "type": "delay"
        },
        "958": {
            "delay": 283.0,
            "type": "delay"
        },
        "959": {
            "delay": 266.0,
            "type": "delay"
        },
        "960": {
            "delay": 388.0,
            "type": "delay"
        },
        "961": {
            "delay": 27.0,
            "type": "delay"
        },
        "962": {
            "delay": 27.0,
            "type": "delay"
        },
        "963": {
            "delay": 596.0,
            "type": "delay"
        },
        "964": {
            "delay": 1177.0,
            "type": "delay"
        },
        "965": {
            "delay": 184.0,
            "type": "delay"
        },
        "966": {
            "delay": 89.0,
            "type": "delay"
        },
        "967": {
            "delay": 594.0,
            "type": "delay"
        },
        "968": {
            "delay": 594.0,
            "type": "delay"
        },
        "969": {
            "delay": 141.0,
            "type": "delay"
        },
        "970": {
            "delay": 5.0,
            "type": "delay"
        },
        "971": {
            "delay": 266.0,
            "type": "delay"
        },
        "972": {
            "delay": 49.0,
            "type": "delay"
        },
        "973": {
            "delay": 4.0,
            "type": "delay"
        },
        "974": {
            "delay": 1180.0,
            "type": "delay"
        },
        "975": {
            "delay": 27.0,
            "type": "delay"
        },
        "976": {
            "delay": 144.0,
            "type": "delay"
        },
        "977": {
            "delay": 36.0,
            "type": "delay"
        },
        "978": {
            "delay": 62.0,
            "type": "delay"
        },
        "979": {
            "delay": 20.0,
            "type": "delay"
        },
        "980": {
            "delay": 266.0,
            "type": "delay"
        },
        "981": {
            "delay": 89.0,
            "type": "delay"
        },
        "982": {
            "delay": 597.0,
            "type": "delay"
        },
        "983": {
            "delay": 7.0,
            "type": "delay"
        },
        "984": {
            "delay": 62.0,
            "type": "delay"
        },
        "985": {
            "delay": 10.0,
            "type": "delay"
        },
        "986": {
            "delay": 5.0,
            "type": "delay"
        },
        "987": {
            "delay": 592.0,
            "type": "delay"
        },
        "988": {
            "delay": 27.0,
            "type": "delay"
        },
        "989": {
            "delay": 387.0,
            "type": "delay"
        },
        "990": {
            "delay": 1177.0,
            "type": "delay"
        },
        "991": {
            "delay": 62.0,
            "type": "delay"
        },
        "992": {
            "delay": 388.0,
            "type": "delay"
        },
        "993": {
            "delay": 90.0,
            "type": "delay"
        },
        "994": {
            "delay": 281.0,
            "type": "delay"
        },
        "995": {
            "delay": 141.0,
            "type": "delay"
        },
        "996": {
            "delay": 27.0,
            "type": "delay"
        },
        "997": {
            "delay": 1178.0,
            "type": "delay"
        },
        "998": {
            "delay": 183.0,
            "type": "delay"
        },
        "999": {
            "delay": 266.0,
            "type": "delay"
        }
    }
}